{
  "NIFTY": {
    "asset": "NIFTY",
    "timestamp": 1767765236307,
    "futures": 26251,
    "headline": {
      "weekly": 0.07946536689393649
    },
    "weekly": {
      "expiry": "2026-01-13",
      "atmStrike": 26250,
      "indiv": 0.07946536689393649,
      "rows": [
        {
          "strike": 26150,
          "call": {
            "price": 110.6,
            "iv": 0.031990231323242184,
            "greeks": {
              "delta": 0.8310875295867086,
              "gamma": 0.0023819403714151117,
              "vega": 833.488132038715,
              "theta": -839.8995616965086
            }
          },
          "put": {
            "price": 91.15,
            "iv": 0.10309476623535158,
            "greeks": {
              "delta": -0.38083750341670175,
              "gamma": 0.00111744114221889,
              "vega": 1260.1215246664092,
              "theta": -4092.225921428975
            }
          },
          "weight": 0.7934136300730442
        },
        {
          "strike": 26200,
          "call": {
            "price": 85.3,
            "iv": 0.04259487762451172,
            "greeks": {
              "delta": 0.6424663427292161,
              "gamma": 0.00264934357367178,
              "vega": 1234.3741314615822,
              "theta": -1656.2074747827746
            }
          },
          "put": {
            "price": 116.2,
            "iv": 0.10637534027099609,
            "greeks": {
              "delta": -0.4396708129653323,
              "gamma": 0.0011209584043634293,
              "vega": 1304.3123734033372,
              "theta": -4370.52018502419
            }
          },
          "weight": 0.9620840585022294
        },
        {
          "strike": 26250,
          "call": {
            "price": 64.45,
            "iv": 0.04846939392089843,
            "greeks": {
              "delta": 0.5037067677731737,
              "gamma": 0.0024885602072925593,
              "vega": 1319.3708847551206,
              "theta": -2014.396874940247
            }
          },
          "put": {
            "price": 145.25,
            "iv": 0.11049513092041015,
            "greeks": {
              "delta": -0.496131494126262,
              "gamma": 0.0010916186050948969,
              "vega": 1319.3658061086087,
              "theta": -4592.18017055332
            }
          },
          "weight": 1
        },
        {
          "strike": 26300,
          "call": {
            "price": 47.25,
            "iv": 0.052284014892578126,
            "greeks": {
              "delta": 0.38981140562959987,
              "gamma": 0.002218524438509945,
              "vega": 1268.7740902881983,
              "theta": -2089.6030081062804
            }
          },
          "put": {
            "price": 178.9,
            "iv": 0.1159881851196289,
            "greeks": {
              "delta": -0.5478806314075622,
              "gamma": 0.001032470663253349,
              "vega": 1309.9135299517995,
              "theta": -4785.936529586809
            }
          },
          "weight": 0.9772432502145275
        },
        {
          "strike": 26350,
          "call": {
            "price": 34,
            "iv": 0.05525941925048827,
            "greeks": {
              "delta": 0.295567062533631,
              "gamma": 0.0018895769109260568,
              "vega": 1142.1471080852132,
              "theta": -1988.1031555795262
            }
          },
          "put": {
            "price": 215.2,
            "iv": 0.12171011657714845,
            "greeks": {
              "delta": -0.5939866978878572,
              "gamma": 0.0009634453662691373,
              "vega": 1282.6404301985183,
              "theta": -4917.474963009803
            }
          },
          "weight": 0.9189198553532195
        },
        {
          "strike": 26400,
          "call": {
            "price": 24.25,
            "iv": 0.05808223876953124,
            "greeks": {
              "delta": 0.22070892941808973,
              "gamma": 0.0015442268678204506,
              "vega": 981.0826754436695,
              "theta": -1794.9795635447465
            }
          },
          "put": {
            "price": 255.35,
            "iv": 0.12895789642333988,
            "greeks": {
              "delta": -0.6331621503001348,
              "gamma": 0.0008827725715367091,
              "vega": 1245.2252703214065,
              "theta": -5058.32139016575
            }
          },
          "weight": 0.8437021979015062
        },
        {
          "strike": 26450,
          "call": {
            "price": 17.25,
            "iv": 0.06082876586914063,
            "greeks": {
              "delta": 0.16314794318868836,
              "gamma": 0.0012248836026694488,
              "vega": 814.9950681675292,
              "theta": -1561.6170418611084
            }
          },
          "put": {
            "price": 298,
            "iv": 0.1369686004638672,
            "greeks": {
              "delta": -0.6660421013304775,
              "gamma": 0.0008032441198817912,
              "vega": 1203.4269352403596,
              "theta": -5192.198647032379
            }
          },
          "weight": 0.7649198233368275
        },
        {
          "strike": 26500,
          "call": {
            "price": 12.25,
            "iv": 0.06342270812988282,
            "greeks": {
              "delta": 0.11950056621802796,
              "gamma": 0.0009508677635646054,
              "vega": 659.6537884499261,
              "theta": -1317.8664352863802
            }
          },
          "put": {
            "price": 343.25,
            "iv": 0.14619998321533204,
            "greeks": {
              "delta": -0.6926327381377797,
              "gamma": 0.0007269014711216428,
              "vega": 1162.449312725141,
              "theta": -5353.427205286331
            }
          },
          "weight": 0.6905210010092533
        },
        {
          "strike": 26550,
          "call": {
            "price": 8.85,
            "iv": 0.0661692352294922,
            "greeks": {
              "delta": 0.0878062712301434,
              "gamma": 0.0007285347828658045,
              "vega": 527.2997447077233,
              "theta": -1099.0671565865205
            }
          },
          "put": {
            "price": 390,
            "iv": 0.15604170532226563,
            "greeks": {
              "delta": -0.71439293161135,
              "gamma": 0.0006585131097606193,
              "vega": 1123.9740067978214,
              "theta": -5524.684853896902
            }
          },
          "weight": 0.6257819346745954
        },
        {
          "strike": 26600,
          "call": {
            "price": 6.6,
            "iv": 0.06937351684570313,
            "greeks": {
              "delta": 0.06594360319894588,
              "gamma": 0.0005588355223622193,
              "vega": 424.0615242783226,
              "theta": -926.6871378913078
            }
          },
          "put": {
            "price": 436.6,
            "iv": 0.16512050323486327,
            "greeks": {
              "delta": -0.7338366799276296,
              "gamma": 0.0006011147146185546,
              "vega": 1085.69919842775,
              "theta": -5647.0427371914475
            }
          },
          "weight": 0.5721528517541806
        },
        {
          "strike": 26650,
          "call": {
            "price": 5.15,
            "iv": 0.07303555297851562,
            "greeks": {
              "delta": 0.051046249906660734,
              "gamma": 0.0004340741824977548,
              "vega": 346.77631902278085,
              "theta": -797.8005069200126
            }
          },
          "put": {
            "price": 485.15,
            "iv": 0.17557256469726562,
            "greeks": {
              "delta": -0.7488589203797342,
              "gamma": 0.000548576872113354,
              "vega": 1053.5261056219604,
              "theta": -5826.563830696452
            }
          },
          "weight": 0.5306715253147841
        },
        {
          "strike": 26700,
          "call": {
            "price": 4.25,
            "iv": 0.07730792846679686,
            "greeks": {
              "delta": 0.04124910799620446,
              "gamma": 0.00034555334246900277,
              "vega": 292.20678017565206,
              "theta": -711.5818770689688
            }
          },
          "put": {
            "price": 533.4,
            "iv": 0.185261701965332,
            "greeks": {
              "delta": -0.7626747359263317,
              "gamma": 0.0005042648034383452,
              "vega": 1021.8695555346392,
              "theta": -5963.368730914493
            }
          },
          "weight": 0.49799449117454714
        },
        {
          "strike": 26750,
          "call": {
            "price": 3.4,
            "iv": 0.08066479492187499,
            "greeks": {
              "delta": 0.03231622002455847,
              "gamma": 0.00027122994994877443,
              "vega": 239.3166045182797,
              "theta": -608.0893819832945
            }
          },
          "put": {
            "price": 581.2,
            "iv": 0.19418791503906252,
            "greeks": {
              "delta": -0.7756076124573847,
              "gamma": 0.0004662628565896501,
              "vega": 990.3852721593216,
              "theta": -6058.106809209414
            }
          },
          "weight": 0.4660191677840682
        }
      ]
    }
  },
  "BANKNIFTY": {
    "asset": "BANKNIFTY",
    "timestamp": 1767765299473,
    "futures": 60183.2,
    "headline": {
      "weekly": 0
    },
    "weekly": null
  }
}